pynetcat/__init__.py
pynetcat/example.py
pynetcat-0.0.4.dist-info/METADATA
pynetcat-0.0.4.dist-info/WHEEL
pynetcat-0.0.4.dist-info/licenses/LICENSE
pynetcat-0.0.4.dist-info/RECORD
